MANIFEST.in
README.md
setup.cfg
setup.py
powerpack/__init__.py
powerpack/cells.py
powerpack/electrical.py
powerpack/mechanical.py
powerpack/power_profile.py
powerpack/thermal.py
powerpack.egg-info/PKG-INFO
powerpack.egg-info/SOURCES.txt
powerpack.egg-info/dependency_links.txt
powerpack.egg-info/requires.txt
powerpack.egg-info/top_level.txt
powerpack/models/electrical_battery.py
powerpack/models/electrical_cell.py
powerpack/models/workflows/workflow_battery.py
powerpack/optimization/__init__.py
powerpack/optimization/electrical.py
powerpack/optimization/mechanical.py
powerpack/optimization/thermal.py
scripts/api_elec_battery.py
scripts/elec_battery_complex.py
scripts/elec_battery_simple.py
scripts/elec_cell_complex.py
scripts/elec_cell_simple.py
scripts/elec_module.py