Metadata-Version: 1.0
Name: powerpack
Version: 0.2.1.post2
Summary: Generative Design of battery packs
Home-page: UNKNOWN
Author: Dessia Technologies
Author-email: root@dessia.tech
License: UNKNOWN
Platform: UNKNOWN
